hotckissast/__init__.py
hotckissast/build_ast.py
hotckissast/fibonacci.py
hotckissast/visitor.py
hotckissast-1.0.1.dist-info/METADATA
hotckissast-1.0.1.dist-info/WHEEL
hotckissast-1.0.1.dist-info/top_level.txt
hotckissast-1.0.1.dist-info/RECORD
